rm_teng/__init__.py
rm_teng-1.0.3.dist-info/WHEEL
rm_teng-1.0.3.dist-info/entry_points.txt
rm_teng-1.0.3.dist-info/METADATA
rm_teng-1.0.3.dist-info/RECORD
