Metadata-Version: 2.3
Name: rm-teng
Version: 1.0.3
Summary: Add your description here
Author: geo7
Author-email: geo7 <georgelenton@gmail.com>
Requires-Python: >=3.14
